orto/__init__.py
orto/__version__.py
orto/cli.py
orto/constants.py
orto/data.py
orto/exceptions.py
orto/extractor.py
orto/input.py
orto/job.py
orto/plotter.py
orto/utils.py
orto-1.14.0.dist-info/licenses/LICENSE
orto-1.14.0.dist-info/METADATA
orto-1.14.0.dist-info/WHEEL
orto-1.14.0.dist-info/entry_points.txt
orto-1.14.0.dist-info/top_level.txt
orto-1.14.0.dist-info/RECORD
