Metadata-Version: 2.4
Name: orto
Version: 1.14.0
Summary: A package to make life easier when performing Orca calculations.
Home-page: https://orto.kragskow.group
Author: Jon Kragskow
Author-email: jgck20@bath.ac.uk
Project-URL: Bug Tracker, https://gitlab.com/kragskow-group/orto/issues
Project-URL: Documentation, https://orto.kragskow.group
Classifier: Programming Language :: Python :: 3
Classifier: License :: OSI Approved :: GNU General Public License v3 (GPLv3)
Classifier: Operating System :: OS Independent
Requires-Python: >=3.10
License-File: LICENSE
Requires-Dist: numpy>=2.1.2
Requires-Dist: xyz_py>=5.19.2
Requires-Dist: matplotlib>=3.9.2
Requires-Dist: extto>=1.1.0
Requires-Dist: pandas>=2.2.3
Requires-Dist: subto>=0.1.1
Requires-Dist: python-docx>=1.2.0
Dynamic: author
Dynamic: author-email
Dynamic: classifier
Dynamic: description
Dynamic: description-content-type
Dynamic: home-page
Dynamic: license-file
Dynamic: project-url
Dynamic: requires-dist
Dynamic: requires-python
Dynamic: summary
